setup.py
Admire.egg-info/PKG-INFO
Admire.egg-info/SOURCES.txt
Admire.egg-info/dependency_links.txt
Admire.egg-info/requires.txt
Admire.egg-info/top_level.txt
admire/__init__.py