Metadata-Version: 1.0
Name: Admire
Version: 1.0.0
Summary: An intuitive reCAPTCHA interface.
Home-page: https://github.com/Avlyssna/Admire
Author: Avlyssna
Author-email: avlyssna@gmail.com
License: MIT
Keywords: reCAPTCHA CAPTCHA
Platform: UNKNOWN
